discord/ext/test/__init__.py
discord/ext/test/_types.py
discord/ext/test/backend.py
discord/ext/test/callbacks.py
discord/ext/test/factories.py
discord/ext/test/runner.py
discord/ext/test/state.py
discord/ext/test/utils.py
discord/ext/test/verify.py
discord/ext/test/websocket.py
testcord-0.0.1.dist-info/LICENSE
testcord-0.0.1.dist-info/METADATA
testcord-0.0.1.dist-info/WHEEL
testcord-0.0.1.dist-info/top_level.txt
testcord-0.0.1.dist-info/RECORD
