Metadata-Version: 2.1
Name: testcord
Version: 0.0.1
Summary: A package that assists in writing tests for pycord
Home-page: https://github.com/KoalaBotUK/testcord
Author: KoalaBotUK
Author-email: KoalaBotUK@gmail.com
License: UNKNOWN
Keywords: discord pycord test
Platform: UNKNOWN
Classifier: Programming Language :: Python :: 3.6
Classifier: Programming Language :: Python :: 3.7
Classifier: Programming Language :: Python :: 3.8
Classifier: Programming Language :: Python :: 3.9
Classifier: License :: OSI Approved :: MIT License
Classifier: Operating System :: OS Independent
Classifier: Development Status :: 3 - Alpha
Classifier: Topic :: Software Development :: Testing
License-File: LICENSE
